odoo/addons/report_generate_helper/README.rst
odoo/addons/report_generate_helper/__init__.py
odoo/addons/report_generate_helper/__manifest__.py
odoo/addons/report_generate_helper/i18n/it.po
odoo/addons/report_generate_helper/i18n/report_generate_helper.pot
odoo/addons/report_generate_helper/models/__init__.py
odoo/addons/report_generate_helper/models/base.py
odoo/addons/report_generate_helper/models/ir_actions_report.py
odoo/addons/report_generate_helper/readme/CONTRIBUTORS.rst
odoo/addons/report_generate_helper/readme/DESCRIPTION.rst
odoo/addons/report_generate_helper/static/description/icon.png
odoo/addons/report_generate_helper/static/description/index.html
odoo/addons/report_generate_helper/tests/__init__.py
odoo/addons/report_generate_helper/tests/test_report_generate_helper.py
odoo_addon_report_generate_helper-16.0.1.0.0.5.dist-info/METADATA
odoo_addon_report_generate_helper-16.0.1.0.0.5.dist-info/WHEEL
odoo_addon_report_generate_helper-16.0.1.0.0.5.dist-info/top_level.txt
odoo_addon_report_generate_helper-16.0.1.0.0.5.dist-info/RECORD
